{
  "revenue": {
    "opening": "看到你们2026年预计营收5000万，2028年要到1.5亿，这个增长主要靠电子特气、液相还是氢能哪个板块拉动？",
    "follow_up": "如果不算新客户，现有业务明年大概能贡献多少增长？",
    "best_question": "你们去年收入大概多少？今年为什么能到5000万？主要来自老客户放量，还是新客户拓展？"
  },
  "customer": {
    "opening": "BP里提到‘丰富的应用案例’，能具体说下已经落地的头部客户是谁吗？比如在电子特气领域，有进入哪些半导体厂的供应商名录？",
    "follow_up": "前五大客户集中度如何？有没有过于依赖某一家？",
    "best_question": "像中芯国际、华虹这种级别的客户，现在有在测试或采购你们的分子筛吗？大概占收入多少比例？"
  },
  "industry": {
    "opening": "分子筛替代精馏这个方向，除了你们，国内还有中触媒、建龙微纳这些上市公司在做，你们跟他们比核心差异在哪？",
    "follow_up": "下游客户对分子筛法替代精馏的接受度如何？是主动找你们还是需要教育市场？",
    "best_question": "这个赛道目前除了UOP、Zeochem这些国际巨头，国内还有谁在直接竞争？你们的‘独创工艺’具体指什么，能防止被模仿吗？"
  },
  "production": {
    "opening": "本轮融资5000万主要用于建设产线，预计什么时候能投产？达产后产能是多少？",
    "follow_up": "现有产能利用率大概在什么水平？主要瓶颈在哪一环？",
    "best_question": "如果明年订单翻一倍，你们的产能跟得上吗？最大的瓶颈是设备、原料还是工艺放大？"
  },
  "tech": {
    "opening": "你们提到‘能耗下降70%-90%’和‘成本为精馏的50%’，这些数据有没有大规模、长时间、多客户的验证案例？比如客户出具的验收报告？",
    "follow_up": "这个壁垒是分子筛的配方、成型工艺，还是与PSA/TSA工艺的结合方式？",
    "best_question": "如果UOP或建龙微纳想复制你们的工艺，大概需要多久能做到接近水平？他们现在有没有在跟进这个方向？"
  },
  "business_model": {
    "opening": "你们更倾向把自己定义为材料公司，还是工艺解决方案商？",
    "follow_up": "这两种模式的毛利率差异大吗？",
    "best_question": "你们现在是卖分子筛原料的模式，还是已经开始做‘分子筛+工艺包’的整体解决方案了？技术服务这块现在占比多少？"
  },
  "new_business": {
    "opening": "氢能这块，你们提到‘绿氢专用高压分子筛’，这个目前更偏研发合作，还是已经开始稳定出货？",
    "follow_up": "有没有形成复购的客户？",
    "best_question": "电子特气、液相、氢能这几个新业务，哪个已经跑出标杆客户并形成复购了？还是说都还在早期验证阶段？"
  }
}