{
  "company_essence": {
    "是什么": "新能源汽车电驱动系统及核心功率半导体（IGBT/SiC）的全产业链方案提供商，覆盖从芯片设计、模块封装到电机控制器、动力总成的研发、生产与销售。",
    "不是什么": [
      "纯粹的芯片设计公司（Fabless）",
      "纯粹的整车制造企业",
      "纯粹的软件或算法公司"
    ],
    "confidence": "high"
  },
  "business_structure": {
    "current_business": [
      "IGBT/SiC功率模块的封装、测试、生产与销售",
      "电机控制器（单体、双电机、集成式）的研发、生产与销售",
      "集成式动力总成系统的研发、生产与销售",
      "整车控制器（VCU）、多合一辅控系统、DCDC电源模块的研发、生产与销售"
    ],
    "narrative_business": [
      "全产业链（芯片设计→模块封装→系统集成）垂直整合能力",
      "高压平台（800V）SiC产品布局",
      "从商用车（物流车、重卡）向乘用车、非道路车辆（农机、船舶、储能）的跨场景拓展"
    ]
  },
  "revenue_logic": {
    "current_money_source": "销售电机控制器、IGBT/SiC功率模块、动力总成系统及辅助电源产品给整车厂及Tier1供应商，以商用车（物流车、重卡）为主，乘用车及非道路车辆为辅。",
    "clarity": "中高——产品线清晰，客户案例明确，但未披露具体客户名称及收入占比，财务预测偏乐观。",
    "red_flag_note": null
  },
  "customer_logic": {
    "who_pays": "整车厂（商用车、乘用车）、车桥/底盘系统集成商（如陕汽汉德）、非道路车辆制造商（农机、船舶、重载无人机）。",
    "why_pays": "提供高功率密度、高可靠性、高压平台（800V）的国产化电驱动解决方案，具备全产业链自主能力，可降低客户供应链风险并提升整车续航与性能。",
    "sustainability": "中——依赖商用车及非道路车辆市场，乘用车渗透率尚低；SiC高压平台为行业趋势，但竞争激烈，需持续技术迭代与客户绑定。"
  },
  "key_judgement": {
    "statement": "一家有产业根基但成长天花板明显的电驱动系统供应商，技术路线正确但商业化节奏偏慢。",
    "reasoning": "团队来自比亚迪，技术积累扎实，产品已装车20万台套，客户包括陕汽汉德等；但BP中缺乏头部乘用车客户背书，财务预测从2025年0.75亿收入跳增至2029年6.5亿，增长假设过于激进，且未披露当前真实营收与利润。",
    "stance": "hold"
  },
  "red_flags": {
    "flags": [
      "财务预测缺乏历史数据支撑，2025-2029年收入增长曲线陡峭（CAGR超70%），可信度低",
      "未披露当前实际营收、利润及现金流状况",
      "客户名单模糊，未列出具体合作整车厂名称及合同金额",
      "融资用途中‘运营资金’占比过高（40%），可能反映现金流紧张",
      "股权结构复杂（实际控制人持股仅44.91%），且提及‘上市公司收购老股+增资’，暗示退出压力"
    ]
  },
  "must_ask_questions": {
    "questions": [
      "请提供过去3年经审计的财务报表（收入、毛利率、净利润、经营性现金流），以及2024年实际数据。",
      "前五大客户是谁？各自收入占比及合作年限？是否有长期框架协议？",
      "IGBT芯片是自研还是外购？自研芯片在模块中的成本占比及良率如何？",
      "SiC模块的客户验证进展如何？预计何时进入乘用车前装供应链？",
      "本次融资6000-8000万元的具体估值依据是什么？老股转让与增资的比例如何安排？"
    ]
  }
}